{
	"description": "项目配置文件",
	"packOptions": {
		"ignore": []
	},
	"setting": {
		"urlCheck": false,
		"es6": true,
		"postcss": true,
		"preloadBackgroundData": false,
		"minified": true,
		"newFeature": true,
		"coverView": true,
		"autoAudits": false,
		"showShadowRootInWxmlPanel": true,
		"scopeDataCheck": false,
		"checkInvalidKey": true,
		"checkSiteMap": true,
		"uploadWithSourceMap": true,
		"babelSetting": {
			"ignore": [],
			"disablePlugins": [],
			"outputPath": ""
		}
	},
	"compileType": "miniprogram",
	"libVersion": "2.10.4",
	"appid": "wx81d8ee295c9128f4",
	"projectname": "%E8%B4%AD%E7%89%A9",
	"debugOptions": {
		"hidedInDevtools": []
	},
	"isGameTourist": false,
	"simulatorType": "wechat",
	"simulatorPluginLibVersion": {},
	"condition": {
		"search": {
			"current": -1,
			"list": []
		},
		"conversation": {
			"current": -1,
			"list": []
		},
		"plugin": {
			"current": -1,
			"list": []
		},
		"game": {
			"currentL": -1,
			"list": []
		},
		"gamePlugin": {
			"current": -1,
			"list": []
		},
		"miniprogram": {
			"current": -1,
			"list": [
				{
					"id": -1,
					"name": "pages/home/home",
					"pathName": "pages/home/home",
					"query": "",
					"scene": null
				},
				{
					"id": -1,
					"name": "components/scrollText/scrollText",
					"pathName": "components/scrollText/scrollText",
					"query": "",
					"scene": null
				},
				{
					"id": -1,
					"name": "pages/release/release",
					"pathName": "pages/release/release",
					"query": "",
					"scene": null
				},
				{
					"id": -1,
					"name": "pages/release2/release2",
					"pathName": "pages/release2/release2",
					"query": "",
					"scene": null
				},
				{
					"id": -1,
					"name": "pages/category/category",
					"pathName": "pages/category/category",
					"query": "",
					"scene": null
				},
				{
					"id": -1,
					"name": "pages/tabs/tabs",
					"pathName": "pages/tabs/tabs",
					"query": "",
					"scene": null
				},
				{
					"id": -1,
					"name": "pages/mine/mine",
					"pathName": "pages/mine/mine",
					"query": "",
					"scene": null
				},
				{
					"id": -1,
					"name": "pages/certification/certification",
					"pathName": "pages/certification/certification",
					"query": "",
					"scene": null
				},
				{
					"id": -1,
					"name": "pages/certification/certification",
					"pathName": "pages/certification/certification",
					"query": "",
					"scene": null
				},
				{
					"id": -1,
					"name": "pages/main-release/main-release",
					"pathName": "pages/main-release/main-release",
					"query": "",
					"scene": null
				},
				{
					"id": -1,
					"name": "pages/release3/release3",
					"pathName": "pages/release3/release3",
					"query": "",
					"scene": null
				},
				{
					"id": -1,
					"name": "pages/release4/release4",
					"pathName": "pages/release4/release4",
					"scene": null
				}
			]
		}
	}
}